datamatrix/__init__.py
datamatrix/_config.py
datamatrix/_ordered_state.py
datamatrix/functional.py
datamatrix/monkeypatch.py
datamatrix/multidimensional.py
datamatrix/operations.py
datamatrix/plot.py
datamatrix/py3compat.py
datamatrix/series.py
datamatrix/_datamatrix/__init__.py
datamatrix/_datamatrix/_basecolumn.py
datamatrix/_datamatrix/_blinkreconstruct.py
datamatrix/_datamatrix/_callable_values.py
datamatrix/_datamatrix/_datamatrix.py
datamatrix/_datamatrix/_index.py
datamatrix/_datamatrix/_mixedcolumn.py
datamatrix/_datamatrix/_multidimensionalcolumn.py
datamatrix/_datamatrix/_nifticolumn.py
datamatrix/_datamatrix/_numericcolumn.py
datamatrix/_datamatrix/_row.py
datamatrix/_datamatrix/_seriescolumn.py
datamatrix/_datamatrix/_sort.py
datamatrix/_datamatrix/_uninstantiatedcolumn.py
datamatrix/_functional/__init__.py
datamatrix/_functional/_memoize.py
datamatrix/colors/__init__.py
datamatrix/colors/tango.py
datamatrix/convert/__init__.py
datamatrix/convert/_html.py
datamatrix/convert/_json.py
datamatrix/convert/_mne.py
datamatrix/convert/_pandas.py
datamatrix/io/__init__.py
datamatrix/io/_bin.py
datamatrix/io/_excel.py
datamatrix/io/_pickle.py
datamatrix/io/_text.py
datamatrix/rbridge/__init__.py
datamatrix/rbridge/lme4.py
datamatrix-1.0.16.dist-info/licenses/COPYING
datamatrix-1.0.16.dist-info/WHEEL
datamatrix-1.0.16.dist-info/METADATA
datamatrix-1.0.16.dist-info/RECORD
