Metadata-Version: 2.4
Name: datamatrix
Version: 1.0.16
Summary: This file is part of datamatrix.
Keywords: data analysis,scientific software,time series
Author-email: Sebastiaan Mathôt <s.mathot@cogsci.nl>
Requires-Python: >=3.7
License-File: COPYING
Requires-Dist: numpy
Requires-Dist: scipy
Requires-Dist: prettytable
Requires-Dist: openpyxl
Requires-Dist: json-tricks
Requires-Dist: tomlkit
Requires-Dist: psutil
Project-URL: Documentation, https://pydatamatrix.eu
Project-URL: Source, https://github.com/open-cogsci/datamatrix
